django_fsm/__init__.py
django_fsm/management/__init__.py
django_fsm/management/commands/__init__.py
django_fsm/management/commands/graph_transitions.py
django_fsm/models.py
django_fsm/signals.py
django_fsm/tests/__init__.py
django_fsm/tests/test_abstract_inheritance.py
django_fsm/tests/test_basic_transitions.py
django_fsm/tests/test_conditions.py
django_fsm/tests/test_integer_field.py
django_fsm/tests/test_key_field.py
django_fsm/tests/test_protected_field.py
django_fsm/tests/test_protected_fields.py
django_fsm/tests/test_proxy_inheritance.py
django_fsm_2-3.0.0.dist-info/LICENSE
django_fsm_2-3.0.0.dist-info/METADATA
django_fsm_2-3.0.0.dist-info/WHEEL
django_fsm_2-3.0.0.dist-info/RECORD
