Metadata-Version: 2.1
Name: django-fsm-2
Version: 3.0.0
Summary: Django friendly finite state machine support.
Home-page: http://github.com/pfouque/django-fsm-2
License: MIT
Author: Mikhail Podgurskiy
Author-email: kmmbvnr@gmail.com
Requires-Python: >=3.8,<4.0
Classifier: Development Status :: 5 - Production/Stable
Classifier: Environment :: Web Environment
Classifier: Framework :: Django
Classifier: Framework :: Django :: 3.2
Classifier: Framework :: Django :: 4.1
Classifier: Framework :: Django :: 4.2
Classifier: Framework :: Django :: 5.0
Classifier: Intended Audience :: Developers
Classifier: License :: OSI Approved :: MIT License
Classifier: Operating System :: OS Independent
Classifier: Programming Language :: Python
Classifier: Programming Language :: Python :: 3
Classifier: Programming Language :: Python :: 3.8
Classifier: Programming Language :: Python :: 3.9
Classifier: Programming Language :: Python :: 3.10
Classifier: Programming Language :: Python :: 3.11
Classifier: Programming Language :: Python :: 3.12
Classifier: Topic :: Software Development :: Libraries :: Python Modules
Requires-Dist: django (>=3.2)
Project-URL: Documentation, http://github.com/pfouque/django-fsm-2
Project-URL: Repository, http://github.com/pfouque/django-fsm-2
